roboquant/__init__.py
roboquant/account.py
roboquant/asset.py
roboquant/event.py
roboquant/monetary.py
roboquant/order.py
roboquant/run.py
roboquant/signal.py
roboquant/timeframe.py
roboquant/alpaca/__init__.py
roboquant/alpaca/broker.py
roboquant/alpaca/feed.py
roboquant/brokers/__init__.py
roboquant/brokers/broker.py
roboquant/brokers/cryptobroker.py
roboquant/brokers/simbroker.py
roboquant/feeds/__init__.py
roboquant/feeds/cryptofeed.py
roboquant/feeds/csvfeed.py
roboquant/feeds/feed.py
roboquant/feeds/historic.py
roboquant/feeds/live.py
roboquant/feeds/parquet.py
roboquant/feeds/randomwalk.py
roboquant/feeds/sql.py
roboquant/feeds/util.py
roboquant/feeds/yahoo.py
roboquant/feeds/resources/us10.parquet
roboquant/ibkr/__init__.py
roboquant/ibkr/broker.py
roboquant/ibkr/types.py
roboquant/journals/__init__.py
roboquant/journals/alphabeta.py
roboquant/journals/basicjournal.py
roboquant/journals/feedmetric.py
roboquant/journals/journal.py
roboquant/journals/marketmetric.py
roboquant/journals/metric.py
roboquant/journals/metricsjournal.py
roboquant/journals/pnlmetric.py
roboquant/journals/pricemetric.py
roboquant/journals/runmetric.py
roboquant/journals/scorecard.py
roboquant/journals/tensorboard.py
roboquant/ml/__init__.py
roboquant/ml/features.py
roboquant/ml/rl.py
roboquant/ml/strategies.py
roboquant/strategies/__init__.py
roboquant/strategies/buffer.py
roboquant/strategies/cachedstrategy.py
roboquant/strategies/emacrossover.py
roboquant/strategies/ibsstrategy.py
roboquant/strategies/multistrategy.py
roboquant/strategies/strategy.py
roboquant/strategies/tastrategy.py
roboquant/ta/__init__.py
roboquant/traders/__init__.py
roboquant/traders/flextrader.py
roboquant/traders/trader.py
roboquant-1.9.12.dist-info/METADATA
roboquant-1.9.12.dist-info/WHEEL
roboquant-1.9.12.dist-info/licenses/LICENSE
roboquant-1.9.12.dist-info/RECORD
