Metadata-Version: 2.4
Name: roboquant
Version: 1.9.12
Summary: A fast algorithmic trading platform with support for AI based strategies
Project-URL: Homepage, https://roboquant.org
Project-URL: Repository, https://github.com/neurallayer/roboquant.py.git
Project-URL: Issues, https://github.com/neurallayer/roboquant.py/issues
Author-email: roboquant team <info@roboquant.org>
License-Expression: Apache-2.0
License-File: LICENSE
Keywords: AI,algorithmic,crypto,exchange,finance,forex,investment,machine learning,stocks,trading
Classifier: Development Status :: 4 - Beta
Classifier: Intended Audience :: Developers
Classifier: License :: OSI Approved :: Apache Software License
Classifier: Operating System :: OS Independent
Classifier: Programming Language :: Python
Classifier: Programming Language :: Python :: 3
Classifier: Programming Language :: Python :: 3 :: Only
Classifier: Programming Language :: Python :: 3.11
Classifier: Programming Language :: Python :: 3.12
Classifier: Programming Language :: Python :: 3.13
Classifier: Topic :: Office/Business :: Financial
Classifier: Topic :: Office/Business :: Financial :: Investment
Requires-Python: <3.14,>=3.11
Requires-Dist: ccxt>=4.4.100
Requires-Dist: numpy>=2.3.0
Requires-Dist: pyarrow>=21.0.0
Requires-Dist: requests>=2.32.4
Requires-Dist: yfinance~=0.2.65
Provides-Extra: alpaca
Requires-Dist: alpaca-py>=0.42.0; extra == 'alpaca'
Provides-Extra: ibkr
Requires-Dist: ibind[oauth]>=0.1.15; extra == 'ibkr'
Provides-Extra: torch
Requires-Dist: sb3-contrib>=2.7.0; extra == 'torch'
Requires-Dist: stable-baselines3[extra]>=2.7.0; extra == 'torch'
Requires-Dist: tensorboard>=2.20.0; extra == 'torch'
Requires-Dist: torch>=2.7.0; extra == 'torch'
